ffmpegarm64v8a_mkkk/__init__.py
ffmpegarm64v8a_mkkk/module1.py
fmpegarm64v8a_mkkk-0.2.0.dist-info/License
fmpegarm64v8a_mkkk-0.2.0.dist-info/METADATA
fmpegarm64v8a_mkkk-0.2.0.dist-info/WHEEL
fmpegarm64v8a_mkkk-0.2.0.dist-info/top_level.txt
fmpegarm64v8a_mkkk-0.2.0.dist-info/RECORD
