Metadata-Version: 2.1
Name: fmpegarm64v8a-mkkk
Version: 0.2.0
Summary: ffmpe on garm64 v8a
Home-page: https://github.com/ffmpegarm64v8a/my_package
Author: okfromhere
Author-email: okfromhere999888@gmail.com 
License: UNKNOWN
Platform: UNKNOWN
Classifier: Programming Language :: Python :: 3
Classifier: License :: OSI Approved :: MIT License
Classifier: Operating System :: OS Independent
Requires-Python: >=3.6
Requires-Dist: requests>=2.0.0
